MACC/Radix_4_Booth_Encode/cla/cla.v
module cla_nbit #(
    parameter N = 16  // Tổng số bit, phải là bội số của 4
)(
    input  [N-1:0] A, B,
    input         Cin,
    output [N-1:0] S,
    output        Cout
);
    localparam NUM_BLOCKS = N / 4;

    wire [NUM_BLOCKS-1:0] carry;

    genvar i;
    generate
        for (i = 0; i < NUM_BLOCKS; i = i + 1) begin : cla_block
            cla_4bit cla_inst (
                .A(A[i*4 + 3 : i*4]),
                .B(B[i*4 + 3 : i*4]),
                .Cin((i == 0) ? Cin : carry[i-1]),
                .S(S[i*4 + 3 : i*4]),
                .Cout(carry[i])
            );
        end
    endgenerate

    assign Cout = carry[NUM_BLOCKS-1];
endmodule


// 4_bit_CLA
module cla_4bit(
    input [3:0] A, B,
    input Cin,
    output [3:0] S,
    output Cout
);
    wire G[3:0], P[3:0];
    wire C[4:0];

    assign G[0] = A[0] & B[0];
    assign G[1] = A[1] & B[1];
    assign G[2] = A[2] & B[2];
    assign G[3] = A[3] & B[3];

    assign P[0] = A[0] ^ B[0];
    assign P[1] = A[1] ^ B[1];
    assign P[2] = A[2] ^ B[2];
    assign P[3] = A[3] ^ B[3];
    
    assign C[0] = Cin;
    assign C[1] = G[0] | (P[0] & Cin);
    assign C[2] = G[1] | (P[1] & (G[0] | (P[0] & Cin)));
    assign C[3] = G[2] | (P[2] & (G[1] | (P[1] & (G[0] | (P[0] & Cin)))));
    assign Cout = G[3] | (P[3] & (G[2] | (P[2] & (G[1] | (P[1] & (G[0] | (P[0] & Cin)))))));

    assign S[0] = P[0] ^ C[0];
    assign S[1] = P[1] ^ C[1];
    assign S[2] = P[2] ^ C[2];
    assign S[3] = P[3] ^ C[3];
   
endmodule

MACC/Radix_4_Booth_Encode/cla/cla_tb.v
`timescale 1ns / 1ps

module tb_cla_nbit;
    parameter N = 16;

    // Tín hiệu gốc
    reg  [N-1:0] A, B;
    reg          Cin;
    wire [N-1:0] S;
    wire         Cout;

    // Tín hiệu có dấu để hiển thị đúng số âm
    wire signed [N-1:0] As, Bs, Ss;

    assign As = A;
    assign Bs = B;
    assign Ss = S;

    // Khởi tạo module DUT
    cla_nbit #(N) dut (
        .A(A),
        .B(B),
        .Cin(Cin),
        .S(S),
        .Cout(Cout)
    );

    // Ghi tín hiệu vào file .vcd để xem waveform
    initial begin
        $dumpfile("tb_cla_nbit.vcd");
        $dumpvars(0, tb_cla_nbit);
    end

    // Hiển thị kết quả đầu ra
    initial begin
        $display("Time  | Cin |         A         |         B         |         S         | Cout");
        $monitor("%5t |  %b  | %b (%0d) | %b (%0d) | %b (%0d) |  %b", 
                  $time, Cin, A, As, B, Bs, S, Ss, Cout);
    end

    // Các test vector
    initial begin
        A = 16'd10; B = 16'd20; Cin = 0; #10;
        A = 16'd1234; B = 16'd4321; Cin = 0; #10;

        A = -16'sd15; B = 16'd5; Cin = 0; #10;
        A = -16'sd100; B = 16'd50; Cin = 0; #10;

        A = 16'd30; B = -16'sd10; Cin = 0; #10;
        A = 16'd5; B = -16'sd8; Cin = 0; #10;

        A = -16'sd25; B = -16'sd15; Cin = 0; #10;

        A = 16'sd32767; B = 16'sd1; Cin = 0; #10;
        A = -16'sd32768; B = -16'sd1; Cin = 0; #10;

        $finish;
    end
endmodule

MACC/Radix_4_Booth_Encode/cla/tb_cla_nbit.vcd
$date
	Tue Apr 08 13:47:33 2025
$end
$version
	Icarus Verilog
$end
$timescale
	1ps
$end
$scope module tb_cla_nbit $end
$var wire 16 ! As [15:0] $end
$var wire 16 " Bs [15:0] $end
$var wire 1 # Cout $end
$var wire 16 $ S [15:0] $end
$var wire 16 % Ss [15:0] $end
$var reg 16 & A [15:0] $end
$var reg 16 ' B [15:0] $end
$var reg 1 ( Cin $end
$scope module dut $end
$var wire 16 ) A [15:0] $end
$var wire 16 * B [15:0] $end
$var wire 1 + Cin $end
$var wire 1 # Cout $end
$var wire 16 , S [15:0] $end
$var wire 4 - carry [3:0] $end
$scope begin cla_block[0] $end
$scope module cla_inst $end
$var wire 4 . A [3:0] $end
$var wire 4 / B [3:0] $end
$var wire 1 + Cin $end
$var wire 1 0 Cout $end
$var wire 4 1 S [3:0] $end
$upscope $end
$upscope $end
$scope begin cla_block[1] $end
$scope module cla_inst $end
$var wire 4 2 A [3:0] $end
$var wire 4 3 B [3:0] $end
$var wire 1 4 Cin $end
$var wire 1 5 Cout $end
$var wire 4 6 S [3:0] $end
$upscope $end
$upscope $end
$scope begin cla_block[2] $end
$scope module cla_inst $end
$var wire 4 7 A [3:0] $end
$var wire 4 8 B [3:0] $end
$var wire 1 9 Cin $end
$var wire 1 : Cout $end
$var wire 4 ; S [3:0] $end
$upscope $end
$upscope $end
$scope begin cla_block[3] $end
$scope module cla_inst $end
$var wire 4 < A [3:0] $end
$var wire 4 = B [3:0] $end
$var wire 1 > Cin $end
$var wire 1 ? Cout $end
$var wire 4 @ S [3:0] $end
$upscope $end
$upscope $end
$upscope $end
$upscope $end
$enddefinitions $end
#0
$dumpvars
b0 @
0?
0>
b0 =
b0 <
b0 ;
0:
09
b0 8
b0 7
b1 6
05
04
b1 3
b0 2
b1110 1
00
b100 /
b1010 .
b0 -
b11110 ,
0+
b10100 *
b1010 )
0(
b10100 '
b1010 &
b11110 %
b11110 $
0#
b10100 "
b1010 !
$end
#10000
19
b1011 6
b1 @
b11 1
15
b10 -
b1010110110011 %
b1010110110011 $
b1010110110011 ,
b101 ;
b1 /
b1110 3
b1 =
b10 .
b1101 2
b100 7
b1000011100001 '
b1000011100001 *
b1000011100001 "
b10011010010 &
b10011010010 )
b10011010010 !
#20000
0#
0?
0>
0:
09
05
b0 -
b1111 6
b110 1
b1111 ;
b1111111111110110 %
b1111111111110110 $
b1111111111110110 ,
b1111 @
b101 /
b0 3
b0 =
b1 .
b1111 2
b1111 7
b1111 <
b101 '
b101 *
b101 "
b1111111111110001 &
b1111111111110001 )
b1111111111110001 !
#30000
b1110 1
b1111111111001110 %
b1111111111001110 $
b1111111111001110 ,
b1100 6
b10 /
b11 3
b1100 .
b1001 2
b110010 '
b110010 *
b110010 "
b1111111110011100 &
b1111111110011100 )
b1111111110011100 !
#40000
1#
1?
b0 @
1>
1:
b0 ;
19
14
15
10
b1111 -
b1 6
b10100 %
b10100 $
b10100 ,
b100 1
b110 /
b1111 3
b1111 8
b1111 =
b1110 .
b1 2
b0 7
b0 <
b1111111111110110 '
b1111111111110110 *
b1111111111110110 "
b11110 &
b11110 )
b11110 !
#50000
0#
0?
b1111 @
0>
0:
b1111 ;
09
05
04
00
b0 -
b1101 1
b1111111111111101 %
b1111111111111101 $
b1111111111111101 ,
b1111 6
b1000 /
b101 .
b0 2
b1111111111111000 '
b1111111111111000 *
b1111111111111000 "
b101 &
b101 )
b101 !
#60000
19
1>
1#
b1000 1
15
b1101 6
1:
b1111 ;
1?
b1110 -
b1111111111011000 %
b1111111111011000 $
b1111111111011000 ,
b1111 @
b1 /
b111 .
b1110 2
b1111 7
b1111 <
b1111111111110001 '
b1111111111110001 *
b1111111111110001 "
b1111111111100111 &
b1111111111100111 )
b1111111111100111 !
#70000
1>
1:
19
15
14
10
0#
b0 6
b0 ;
b1000 @
b1000000000000000 %
b1000000000000000 $
b1000000000000000 ,
b0 1
0?
b111 -
b0 3
b0 8
b0 =
b1111 .
b1111 2
b111 <
b1 '
b1 *
b1 "
b111111111111111 &
b111111111111111 )
b111111111111111 !
#80000
b111 @
0>
0:
b1111 ;
09
05
b1111 6
04
00
1#
b111111111111111 %
b111111111111111 $
b111111111111111 ,
b1111 1
1?
b1000 -
b1111 /
b1111 3
b1111 8
b1111 =
b0 .
b0 2
b0 7
b1000 <
b1111111111111111 '
b1111111111111111 *
b1111111111111111 "
b1000000000000000 &
b1000000000000000 )
b1000000000000000 !
