MACC/Radix_4_Booth_Encode/d_flip_flop/dff.v
module dff #(parameter N = 9) (clk, rst_n, d, q);
input clk;
input rst_n;
input [N-1:0] d;
output reg [N-1:0] q;

//Flip Flop with asynchronous reset: 
always @(posedge clk or negedge rst_n) begin
    if (~rst_n) 
        q <= 0; 
    else 
        q <= d; 
end

// //Flip Flop with synchronous reset: 
// always @(posedge clk) 
// if (~rst_n) 
// q <= 0; 
// else 
// q <= d;

endmodule

MACC/Multiplier/orther_module/d_flip_flop/dff_tb.v
`timescale 1ns/1ps

module dff_tb;

    parameter N = 9;

    // Khai báo tín hiệu
    reg clk;
    reg rst_n;
    reg [N-1:0] d;
    wire [N-1:0] q;

    // Khởi tạo module D Flip-Flop
    dff #(N) dut (
        .clk(clk),
        .rst_n(rst_n),
        .d(d),
        .q(q)
    );

    // Tạo xung clock: chu kỳ 10ns
    always #5 clk = ~clk;

    initial begin
    $dumpfile("dff.vcd");
    $dumpvars(0, dff_tb); // dff_tb là tên module testbench
    end 


    initial begin
        $display("Time\tclk\trst_n\td\t\tq");
        $monitor("%0dns\t%b\t%b\t%h\t%h", $time, clk, rst_n, d, q);

        // Khởi tạo tín hiệu
        clk = 0;
        rst_n = 0;
        d = 0;

        // Giai đoạn reset
        #7 rst_n = 1;     // Hủy reset không đồng bộ

        // Nhập dữ liệu d và kiểm tra q cập nhật theo clock
        #3  d = 9'h1A3;   // Chờ tới cạnh lên clk
        #10 d = 9'h055;
        #10 d = 9'h0F0;

        // Reset bất đồng bộ giữa chừng
        #6  rst_n = 0;    // Reset khi clk đang ở giữa
        #10 rst_n = 1;    // Bỏ reset

        // Tiếp tục test sau reset
        #10 d = 9'h1E1;

        #10 $finish;
    end

endmodule

MACC/Radix_4_Booth_Encode/d_flip_flop/dff_tb.vcd
$date
	Sun Apr 06 13:24:30 2025
$end
$version
	Icarus Verilog
$end
$timescale
	1ps
$end
$scope module dff_tb $end
$var wire 9 ! q [8:0] $end
$var reg 1 " clk $end
$var reg 9 # d [8:0] $end
$var reg 1 $ rst_n $end
$scope module dut $end
$var wire 1 % clk $end
$var wire 9 & d [8:0] $end
$var wire 1 ' rst_n $end
$var reg 9 ( q [8:0] $end
$upscope $end
$upscope $end
$enddefinitions $end
#0
$dumpvars
b0 (
0'
b0 &
0%
0$
b0 #
0"
b0 !
$end
#5000
1"
1%
#7000
1$
1'
#10000
b110100011 #
b110100011 &
0"
0%
#15000
b110100011 (
b110100011 !
1"
1%
#20000
0"
0%
b1010101 #
b1010101 &
#25000
b1010101 (
b1010101 !
1"
1%
#30000
0"
0%
b11110000 #
b11110000 &
#35000
b11110000 (
b11110000 !
1"
1%
#36000
b0 (
b0 !
0$
0'
#40000
0"
0%
#45000
1"
1%
#46000
1$
1'
#50000
0"
0%
#55000
b11110000 (
b11110000 !
1"
1%
#56000
b111100001 #
b111100001 &
#60000
0"
0%
#65000
b111100001 (
b111100001 !
1"
1%
