MACC/Radix_4_Booth_Encode/radix4booth.v
module Mul (
    input [7:0] x,
    input [7:0] y,
    output [14:0] o_mul
);

// output - multiply by 2
wire [8:0] m_2x;

// output - wire booth encoder
wire [2:0] o_s1_be;
wire [2:0] o_s2_be;
wire [2:0] o_s3_be;
wire [2:0] o_s4_be;

// output - wire mod bec
wire [8:0] o_s1_bec;

// output - wire mux3to1
wire [8:0] o_s1_mux3to1;
wire [8:0] o_s2_mux3to1;
wire [8:0] o_s3_mux3to1;
wire [8:0] o_s4_mux3to1;

// output - wire of each stage of multiplier
wire [8:0] o_s1;
wire [9:0] o_s2;
wire [9:0] o_s3;
wire [9:0] o_s4;

wire [8:0] o_s1_mux3to1_not;

// multiply 2
multiplier_by_n #( .N(8), .S(1)) mul_2x(
    .A(x),
    .Y(m_2x));

// mux3to1
mux3to1 #(.N(9)) mux_s1(.A(1'b0) , .B(m_2x), .C({x[7],x}),
                        .S0(o_s1_be[0])  , .S1(o_s1_be[1]),
                        .Out(o_s1_mux3to1));

mux3to1 #(.N(9)) mux_s2(.A(1'b0) , .B(m_2x), .C({x[7],x}),
                        .S0(o_s2_be[0])  , .S1(o_s2_be[1]),
                        .Out(o_s2_mux3to1));

mux3to1 #(.N(9)) mux_s3(.A(1'b0) , .B(m_2x), .C({x[7],x}),
                        .S0(o_s3_be[0])  , .S1(o_s3_be[1]),
                        .Out(o_s3_mux3to1));

mux3to1 #(.N(9)) mux_s4(.A(1'b0) , .B(m_2x), .C({x[7],x}),
                        .S0(o_s4_be[0])  , .S1(o_s4_be[1]),
                        .Out(o_s4_mux3to1));

// booth encoder
booth_encoder be_s1( .B0(1'b0), .B1(y[0]), .B2(y[1]), 
                     .P0(o_s1_be[0]), .P1(o_s1_be[1]), .P2(o_s1_be[2]));

booth_encoder be_s2( .B0(y[1]), .B1(y[2]), .B2(y[3]), 
                     .P0(o_s2_be[0]), .P1(o_s2_be[1]), .P2(o_s2_be[2]));

booth_encoder be_s3( .B0(y[3]), .B1(y[4]), .B2(y[5]), 
                     .P0(o_s3_be[0]), .P1(o_s3_be[1]), .P2(o_s3_be[2]));

booth_encoder be_s4( .B0(y[5]), .B1(y[6]), .B2(y[7]), 
                     .P0(o_s4_be[0]), .P1(o_s4_be[1]), .P2(o_s4_be[2]));

// modified BEC of stage 1
assign o_s1_mux3to1_not = ~o_s1_mux3to1;

mod_bec mod_bec_s1(.B(o_s1_mux3to1_not),   // Đầu vào 9-bit
                   .X(o_s1_bec));

// Mux2to1 of stage 1
mux2to1 #(.N(9)) mux2to1_s1(.In0(o_s1_mux3to1), 
                            .In1(o_s1_bec), 
                            .Sel(o_s1_be[2]), 
                            .Out(o_s1));

// sqrt carry save adder using RSA
sqrt_csa_rsa sqrt_csa_rsa_s2(.A({o_s1[8], o_s1[8], o_s1[8:2]}),
                             .B(o_s2_mux3to1), 
                             .Cin(o_s2_be[2]), 
                             .Out(o_s2));

sqrt_csa_rsa sqrt_csa_rsa_s3(.A({o_s2[9],o_s2[9:2]}), 
                             .B(o_s3_mux3to1), 
                             .Cin(o_s3_be[2]), 
                             .Out(o_s3));

sqrt_csa_rsa sqrt_csa_rsa_s4(.A({o_s3[9],o_s3[9:2]}), 
                             .B(o_s4_mux3to1), 
                             .Cin(o_s4_be[2]), 
                             .Out(o_s4));

assign o_mul = {o_s4[8:0], o_s3[1:0], o_s2[1:0], o_s1[1:0]};

endmodule


///////////////////////////////////////////////////////////
module booth_encoder (
    input  wire B0, B1, B2,  
    output wire P0, P1, P2  
);
      
    assign P2 = B2;  // XNOR + XOR 
    assign P1 = B0 ^ B1;               
    assign P0 = (~B2 & B1 & B0) | (B2 & ~(B1 | B0));


endmodule

///////////////////////////////////////////////////////////
module sqrt_csa_rsa (
    A,
    B,
    Cin,
    Out
);

input [8:0] A;
input [8:0] B;
input Cin;
output [9:0] Out;

wire [2:0] o_rsa_2bit;

wire [3:0] o_rsa_3bit;
wire [3:0] o_rsa_3bit_add;
wire [3:0] o_rsa_3bit_sub;

wire [4:0] o_rsa_4bit;
wire [4:0] o_rsa_4bit_add;
wire [4:0] o_rsa_4bit_sub;

rsa #(.N(2)) rsa_2bit(  .A(A[1:0]),
                        .B(B[1:0]),
                        .Cin(Cin),
                        .Sum(o_rsa_2bit[1:0]),
                        .Cout(o_rsa_2bit[2]));

rsa #(.N(3)) rsa_3bit_add(  .A(A[4:2]),
                            .B(B[4:2]),
                            .Cin(0),
                            .Sum(o_rsa_3bit_add[2:0]),
                            .Cout(o_rsa_3bit_add[3]));

rsa #(.N(3)) rsa_3bit_sub(  .A(A[4:2]),
                            .B(B[4:2]),
                            .Cin(1),
                            .Sum(o_rsa_3bit_sub[2:0]),
                            .Cout(o_rsa_3bit_sub[3]));                           

rsa #(.N(4)) rsa_4bit_add(  .A(A[8:5]),
                            .B(B[8:5]),
                            .Cin(0),
                            .Sum(o_rsa_4bit_add[3:0]),
                            .Cout(o_rsa_4bit_add[4]));

rsa #(.N(4)) rsa_4bit_sub(  .A(A[8:5]),
                            .B(B[8:5]),
                            .Cin(1),
                            .Sum(o_rsa_4bit_sub[3:0]),
                            .Cout(o_rsa_4bit_sub[4])); 

mux2to1 #(.N(4)) mux_4bit(  .In0(o_rsa_3bit_add), 
                            .In1(o_rsa_3bit_sub), 
                            .Sel(o_rsa_2bit[2]), 
                            .Out(o_rsa_3bit[3:0]));

mux2to1 #(.N(5)) mux_5bit(  .In0(o_rsa_4bit_add), 
                            .In1(o_rsa_4bit_sub), 
                            .Sel(o_rsa_3bit[3]), 
                            .Out(o_rsa_4bit[4:0])); 

assign Out = {o_rsa_4bit, o_rsa_3bit[2:0], o_rsa_2bit[1:0]};

endmodule


/////////////////////////////////

module rsa #( parameter N = 4 ) (
    input  wire [N-1:0] A, B,  // Các toán hạng đầu vào
    input  wire Cin,           // Bit nhớ vào
    output wire [N-1:0] Sum,   // Tổng đầu ra
    output wire Cout           // Bit nhớ ra
);
    wire [N:0] carry;          // Dây để truyền bit nhớ giữa các bộ cộng
    wire [N-1:0] B_xor;        // B XOR với Cin để hỗ trợ phép trừ khi cần

    assign B_xor = B ^ {N{Cin}};  // Nếu Cin = 1, sẽ thực hiện phép trừ A - B
    assign carry[0] = Cin; 
    

    genvar i;
    generate
        for (i = 0; i < N; i = i + 1) begin : adder_stage
            full_adder FA (
                .A(A[i]), 
                .B(B_xor[i]), 
                .Cin(carry[i]), 
                .Sum(Sum[i]), 
                .Cout(carry[i+1])
            );
        end
    endgenerate

    assign carry_sign = carry[N];  
    assign Cout = carry_sign ^ Cin;  // Xữ lý bit có dấu khi trừ

endmodule


// Full Adder 1-bit
module full_adder (
    input  wire A, B, Cin,  
    output wire Sum, Cout   
);
    assign Sum  = A ^ B ^ Cin; 
    assign Cout = (A & B) | (A & Cin) | (B & Cin);  
endmodule


///////////////////////////
module mux2to1 #(parameter N = 9) (
    input  [N-1:0] In0, In1,
    input  Sel,
    output [N-1:0] Out
);
    assign Out = Sel ? In1 : In0;
endmodule

///////////////////////////////////////////////////////////
module mux3to1 #(parameter N = 9) (
input  wire [N-1:0] A, B, C,  
input  wire S0, S1,         
output wire [N-1:0] Out         
);

assign Out =    (S1 == 0 && S0 == 0) ? A :
                (S1 == 0 && S0 == 1) ? B :
                (S1 == 1 && S0 == 0) ? C : A;

endmodule

///////////////////////////////////////////////////////////
// arithmetic_left_shift 
module multiplier_by_n #(parameter N = 8, parameter S = 1) (
    input  wire [N-1:0] A,
    output wire [N:0] Y
);
    assign Y = {A[N-1], A} << S;  // Dịch trái S bit
endmodule

///////////////////////////////////////////////////////////
// Verilog Code cho 10-bit Modified BEC
module mod_bec (
    input [8:0] B,   // Đầu vào 10-bit
    output [8:0] X   // Đầu ra 10-bit (B + 1)
);
    
    wire [5:0] AND_out; // Tín hiệu trung gian từ các cổng AND
    
    // Cổng NOT cho bit đầu tiên
    assign X[0] = ~B[0];  

    // Nhóm AND-3 và AND-4 theo cấu trúc 2-3-4
    assign AND_out[0] = B[0] & B[1] & B[2];              // 3-input AND
    assign AND_out[1] = B[0] & B[1] & B[2] & B[3];       // 4-input AND
    assign AND_out[2] = B[4] & AND_out[1];               // AND với giá trị trước đó
    assign AND_out[3] = B[5] & B[4] & AND_out[1];        // 3-input AND
    assign AND_out[4] = AND_out[1] & B[6] & B[5] & B[4]; // 4-input AND
    assign AND_out[5] = B[7] & AND_out[4];               // AND với giá trị trước đó
//    assign AND_out[6] = B[8] & B[7] & AND_out[4];        // 3-input AND
//    assign AND_out[7] = B[9] & B[8] & B[7] & AND_out[4]; // 4-input AND

    // Tính toán các giá trị đầu ra X[i]
    assign X[1] = B[1] ^ B[0];
    assign X[2] = B[2] ^ (B[1] & B[0]);
    assign X[3] = B[3] ^ AND_out[0];
    assign X[4] = B[4] ^ AND_out[1];
    assign X[5] = B[5] ^ AND_out[2];
    assign X[6] = B[6] ^ AND_out[3];
    assign X[7] = B[7] ^ AND_out[4];
    assign X[8] = B[8] ^ AND_out[5];
//    assign X[9] = B[9] ^ AND_out[6];

endmodule

MACC/Radix_4_Booth_Encode/sqrt_csa_rsa_tb_next.v
`timescale 1ns/1ps

module sqrt_csa_rsa_tb;

    // Khai báo tín hiệu đầu vào và đầu ra
    reg [8:0] A, B;
    reg Cin;
    wire [9:0] Out;

    // Gọi module sqrt_csa_rsa
    sqrt_csa_rsa UUT (
        .A(A),
        .B(B),
        .Cin(Cin),
        .Out(Out)
    );

    // Ghi dữ liệu mô phỏng vào file VCD
    initial begin
        $dumpfile("sqrt_csa_rsa_tb.vcd");
        $dumpvars(0, sqrt_csa_rsa_tb);

        $display("Time    | A (Bit) | B (Bit) | Cin | o_rsa_2bit | o_rsa_3bit_add | o_rsa_3bit_sub | o_rsa_3bit | o_rsa_4bit_add | o_rsa_4bit_sub | o_rsa_4bit | Out (Dec)");
        $display("------------------------------------------------------------------");

        $monitor("%4t | %b | %b | %b | %b | %b | %b | %b | %b | %b | %b |  %b(%d)", 
                 $time, A, B, Cin, 
                 UUT.o_rsa_2bit, UUT.o_rsa_3bit_add ,UUT.o_rsa_3bit_sub ,UUT.o_rsa_3bit, UUT.o_rsa_4bit_add ,UUT.o_rsa_4bit_sub ,UUT.o_rsa_4bit, Out, Out);

        A = 9'b000110011;  B = 9'b000011101;  Cin = 0;  #10;  // A = 51, B = 29  (Cộng)
        A = 9'b111001110;  B = 9'b000001100;  Cin = 1;  #10;  // A = -26, B = 6  (Trừ)
        A = 9'b000000101;  B = 9'b111110101;  Cin = 0;  #10;  // A = 5, B = -11   (Cộng)
        A = 9'b111101000;  B = 9'b000000011;  Cin = 1;  #10;  // A = -8, B = 3    (Trừ)
        A = 9'b000100100;  B = 9'b000011011;  Cin = 0;  #10;  // A = 36, B = 27   (Cộng)
        A = 9'b111000101;  B = 9'b111100010;  Cin = 1;  #10;  // A = -27, B = -14 (Trừ)
        A = 9'b000011111;  B = 9'b000001000;  Cin = 0;  #10;  // A = 15, B = 8    (Cộng)
        A = 9'b000100101;  B = 9'b000010010;  Cin = 1;  #10;  // A = 37, B = 18   (Trừ)
        A = 9'b111010001;  B = 9'b000010110;  Cin = 0;  #10;  // A = -23, B = 22  (Cộng)
        A = 9'b000000110;  B = 9'b000000011;  Cin = 1;  #10;  // A = 6, B = 3     (Trừ)
        A = 9'b101110011;  B = 9'b110011101;  Cin = 0;  #10;  // A = -77, B = -51  (Cộng)
        A = 9'b110001011;  B = 9'b011110100;  Cin = 1;  #10;  // A = -53, B =  60  (Trừ)
        A = 9'b100101001;  B = 9'b001010101;  Cin = 0;  #10;  // A = -87, B =  21  (Cộng)
        A = 9'b111011110;  B = 9'b000011010;  Cin = 1;  #10;  // A = -18, B =  10  (Trừ)
        A = 9'b010101010;  B = 9'b101011011;  Cin = 0;  #10;  // A = 170, B = -85  (Cộng)

        $finish;
    end
endmodule

MACC/Radix_4_Booth_Encode/sqrt_csa_rsa_tb.vcd
$date
	Sun Mar 30 02:30:55 2025
$end
$version
	Icarus Verilog
$end
$timescale
	1ps
$end
$scope module sqrt_csa_rsa_tb $end
$var wire 10 ! Out [9:0] $end
$var reg 9 " A [8:0] $end
$var reg 9 # B [8:0] $end
$var reg 1 $ Cin $end
$scope module UUT $end
$var wire 9 % A [8:0] $end
$var wire 9 & B [8:0] $end
$var wire 1 ' Cin $end
$var wire 10 ( Out [9:0] $end
$var wire 3 ) o_rsa_2bit [2:0] $end
$var wire 4 * o_rsa_3bit [3:0] $end
$var wire 4 + o_rsa_3bit_add [3:0] $end
$var wire 4 , o_rsa_3bit_sub [3:0] $end
$var wire 5 - o_rsa_4bit [4:0] $end
$var wire 5 . o_rsa_4bit_add [4:0] $end
$var wire 5 / o_rsa_4bit_sub [4:0] $end
$scope module rsa_2bit $end
$var wire 2 0 A [1:0] $end
$var wire 2 1 B [1:0] $end
$var wire 2 2 B_xor [1:0] $end
$var wire 1 ' Cin $end
$var wire 1 3 Cout $end
$var wire 2 4 Sum [1:0] $end
$var wire 3 5 carry [2:0] $end
$var wire 1 6 carry_sign $end
$scope begin adder_stage[0] $end
$scope module FA $end
$var wire 1 7 A $end
$var wire 1 8 B $end
$var wire 1 9 Cin $end
$var wire 1 : Cout $end
$var wire 1 ; Sum $end
$upscope $end
$upscope $end
$scope begin adder_stage[1] $end
$scope module FA $end
$var wire 1 < A $end
$var wire 1 = B $end
$var wire 1 > Cin $end
$var wire 1 ? Cout $end
$var wire 1 @ Sum $end
$upscope $end
$upscope $end
$upscope $end
$scope module rsa_3bit_add $end
$var wire 3 A A [2:0] $end
$var wire 3 B B [2:0] $end
$var wire 3 C B_xor [2:0] $end
$var wire 1 D Cin $end
$var wire 1 E Cout $end
$var wire 3 F Sum [2:0] $end
$var wire 4 G carry [3:0] $end
$var wire 1 H carry_sign $end
$scope begin adder_stage[0] $end
$scope module FA $end
$var wire 1 I A $end
$var wire 1 J B $end
$var wire 1 K Cin $end
$var wire 1 L Cout $end
$var wire 1 M Sum $end
$upscope $end
$upscope $end
$scope begin adder_stage[1] $end
$scope module FA $end
$var wire 1 N A $end
$var wire 1 O B $end
$var wire 1 P Cin $end
$var wire 1 Q Cout $end
$var wire 1 R Sum $end
$upscope $end
$upscope $end
$scope begin adder_stage[2] $end
$scope module FA $end
$var wire 1 S A $end
$var wire 1 T B $end
$var wire 1 U Cin $end
$var wire 1 V Cout $end
$var wire 1 W Sum $end
$upscope $end
$upscope $end
$upscope $end
$scope module rsa_3bit_sub $end
$var wire 3 X A [2:0] $end
$var wire 3 Y B [2:0] $end
$var wire 3 Z B_xor [2:0] $end
$var wire 1 [ Cin $end
$var wire 1 \ Cout $end
$var wire 3 ] Sum [2:0] $end
$var wire 4 ^ carry [3:0] $end
$var wire 1 _ carry_sign $end
$scope begin adder_stage[0] $end
$scope module FA $end
$var wire 1 ` A $end
$var wire 1 a B $end
$var wire 1 b Cin $end
$var wire 1 c Cout $end
$var wire 1 d Sum $end
$upscope $end
$upscope $end
$scope begin adder_stage[1] $end
$scope module FA $end
$var wire 1 e A $end
$var wire 1 f B $end
$var wire 1 g Cin $end
$var wire 1 h Cout $end
$var wire 1 i Sum $end
$upscope $end
$upscope $end
$scope begin adder_stage[2] $end
$scope module FA $end
$var wire 1 j A $end
$var wire 1 k B $end
$var wire 1 l Cin $end
$var wire 1 m Cout $end
$var wire 1 n Sum $end
$upscope $end
$upscope $end
$upscope $end
$scope module rsa_4bit_add $end
$var wire 4 o A [3:0] $end
$var wire 4 p B [3:0] $end
$var wire 4 q B_xor [3:0] $end
$var wire 1 r Cin $end
$var wire 1 s Cout $end
$var wire 4 t Sum [3:0] $end
$var wire 5 u carry [4:0] $end
$var wire 1 v carry_sign $end
$scope begin adder_stage[0] $end
$scope module FA $end
$var wire 1 w A $end
$var wire 1 x B $end
$var wire 1 y Cin $end
$var wire 1 z Cout $end
$var wire 1 { Sum $end
$upscope $end
$upscope $end
$scope begin adder_stage[1] $end
$scope module FA $end
$var wire 1 | A $end
$var wire 1 } B $end
$var wire 1 ~ Cin $end
$var wire 1 !" Cout $end
$var wire 1 "" Sum $end
$upscope $end
$upscope $end
$scope begin adder_stage[2] $end
$scope module FA $end
$var wire 1 #" A $end
$var wire 1 $" B $end
$var wire 1 %" Cin $end
$var wire 1 &" Cout $end
$var wire 1 '" Sum $end
$upscope $end
$upscope $end
$scope begin adder_stage[3] $end
$scope module FA $end
$var wire 1 (" A $end
$var wire 1 )" B $end
$var wire 1 *" Cin $end
$var wire 1 +" Cout $end
$var wire 1 ," Sum $end
$upscope $end
$upscope $end
$upscope $end
$scope module rsa_4bit_sub $end
$var wire 4 -" A [3:0] $end
$var wire 4 ." B [3:0] $end
$var wire 4 /" B_xor [3:0] $end
$var wire 1 0" Cin $end
$var wire 1 1" Cout $end
$var wire 4 2" Sum [3:0] $end
$var wire 5 3" carry [4:0] $end
$var wire 1 4" carry_sign $end
$scope begin adder_stage[0] $end
$scope module FA $end
$var wire 1 5" A $end
$var wire 1 6" B $end
$var wire 1 7" Cin $end
$var wire 1 8" Cout $end
$var wire 1 9" Sum $end
$upscope $end
$upscope $end
$scope begin adder_stage[1] $end
$scope module FA $end
$var wire 1 :" A $end
$var wire 1 ;" B $end
$var wire 1 <" Cin $end
$var wire 1 =" Cout $end
$var wire 1 >" Sum $end
$upscope $end
$upscope $end
$scope begin adder_stage[2] $end
$scope module FA $end
$var wire 1 ?" A $end
$var wire 1 @" B $end
$var wire 1 A" Cin $end
$var wire 1 B" Cout $end
$var wire 1 C" Sum $end
$upscope $end
$upscope $end
$scope begin adder_stage[3] $end
$scope module FA $end
$var wire 1 D" A $end
$var wire 1 E" B $end
$var wire 1 F" Cin $end
$var wire 1 G" Cout $end
$var wire 1 H" Sum $end
$upscope $end
$upscope $end
$upscope $end
$scope module mux_4bit $end
$var wire 4 I" In0 [3:0] $end
$var wire 4 J" In1 [3:0] $end
$var wire 4 K" Out [3:0] $end
$var wire 1 L" Sel $end
$upscope $end
$scope module mux_5bit $end
$var wire 5 M" In0 [4:0] $end
$var wire 5 N" In1 [4:0] $end
$var wire 5 O" Out [4:0] $end
$var wire 1 P" Sel $end
$upscope $end
$upscope $end
$upscope $end
$enddefinitions $end
#0
$dumpvars
1P"
b1 O"
b1 N"
b1 M"
1L"
b1101 K"
b1101 J"
b1011 I"
0H"
1G"
1F"
1E"
0D"
0C"
1B"
1A"
1@"
0?"
0>"
1="
1<"
1;"
0:"
19"
18"
17"
16"
15"
14"
b11111 3"
b1 2"
01"
10"
b1111 /"
b0 ."
b1 -"
0,"
0+"
0*"
0)"
0("
0'"
0&"
0%"
0$"
0#"
0""
0!"
0~
0}
0|
1{
0z
0y
0x
1w
0v
b0 u
b1 t
0s
0r
b0 q
b0 p
b1 o
1n
0m
0l
0k
1j
0i
0h
0g
0f
0e
1d
0c
1b
0a
0`
0_
b1 ^
b101 ]
1\
1[
b0 Z
b111 Y
b100 X
0W
1V
0U
1T
1S
1R
0Q
0P
1O
0N
1M
0L
0K
1J
0I
1H
b1000 G
b11 F
1E
0D
b111 C
b111 B
b100 A
0@
1?
1>
0=
1<
0;
1:
09
18
17
16
b110 5
b0 4
13
b1 2
b1 1
b11 0
b1 /
b1 .
b1 -
b1101 ,
b1011 +
b1101 *
b100 )
b110100 (
0'
b11101 &
b110011 %
0$
b11101 #
b110011 "
b110100 !
$end
#10000
0\
1_
1m
1l
0P"
1h
0E
1P
1U
0H
1g
1L
1Q
0V
b110 G
1c
b1111 ^
b1110 -
b1110 O"
1@
0M
1R
1W
b110 +
b110 I"
b110 F
0d
0i
0n
b0 ,
b0 J"
b0 ]
0{
1""
1'"
1,"
b1110 .
b1110 M"
b1110 t
09"
1>"
1C"
1H"
b1110 /
b1110 N"
b1110 2"
b111011010 !
b111011010 (
b110 *
b110 K"
0T
1k
0;
b10 4
0L"
1=
b11 C
b100 Z
07
1I
1N
0S
1`
1e
0j
0w
1|
1#"
1("
05"
1:"
1?"
1D"
19
03
b10 )
b11 2
b0 1
b11 B
b11 Y
b10 0
b11 A
b11 X
b1110 o
b1110 -"
1$
1'
b111 5
b1100 #
b1100 &
b111001110 "
b111001110 %
#20000
0P"
0E
1\
11"
0H
0_
0<"
0U
0A"
0F"
04"
1@
06
1W
0V
1n
0m
b111 ^
1{
19"
08"
0Q
b10 G
b1111 -
b1111 O"
0="
0B"
0G"
b1 3"
1>
0?
1R
b110 +
b110 I"
b110 F
0i
b1100 ,
b1100 J"
b100 ]
1""
1'"
1,"
b1111 .
b1111 M"
b1111 t
0>"
0C"
0H"
b10001 /
b10001 N"
b1 2"
b111111010 !
b111111010 (
1:
b110 *
b110 K"
0O
1T
1f
0k
1x
1}
1$"
1)"
06"
0;"
0@"
0E"
0;
b10 4
0L"
0=
b101 C
b10 Z
b1111 q
b0 /"
17
0<
0N
0e
0|
0#"
0("
0:"
0?"
0D"
09
03
b10 )
b1 2
b1 1
b101 B
b101 Y
b1111 p
b1111 ."
b1 0
b1 A
b1 X
b0 o
b0 -"
0$
0'
b10 5
b111110101 #
b111110101 &
b101 "
b101 %
#30000
01"
0\
1A"
1F"
14"
0@
0s
1_
1="
1B"
1G"
0>
0P
0U
0~
0%"
0*"
0v
1<"
0W
0n
1m
b1111 ^
0:
0L
0Q
b0 G
0z
0!"
0&"
b1111 -
b1111 O"
0+"
b0 u
18"
b11111 3"
0P"
0M
1R
b10 +
b10 I"
b10 F
0d
1i
b10 ,
b10 J"
b10 ]
1{
1""
1'"
1,"
b1111 .
b1111 M"
b1111 t
19"
1>"
1C"
1H"
b1111 /
b1111 N"
b1111 2"
b111101001 !
b111101001 (
b10 *
b10 K"
0J
0T
1a
1k
0x
0}
0$"
0)"
16"
1;"
1@"
1E"
1;
b1 4
1L"
08
b0 C
b111 Z
b0 q
b1111 /"
07
0I
1N
0`
1e
1w
1|
1#"
1("
15"
1:"
1?"
1D"
19
13
b101 )
b0 2
b11 1
b0 B
b0 Y
b0 p
b0 ."
b0 0
b10 A
b10 X
b1111 o
b1111 -"
1$
1'
b1 5
b11 #
b11 &
b111101000 "
b111101000 %
#40000
1\
0_
0l
1W
0n
0m
b111 *
b111 K"
0h
b11 ^
b1 -
b1 O"
1@
1M
1R
b111 +
b111 I"
b111 F
1d
1i
b1011 ,
b1011 J"
b11 ]
0""
0'"
0,"
b1 .
b1 M"
b1 t
0>"
0C"
0H"
b1 /
b1 N"
b1 2"
b111111 !
b111111 (
1O
1T
0f
0k
1;
b11 4
0L"
18
1=
b110 C
b1 Z
1I
0N
1`
0e
0|
0#"
0("
0:"
0?"
0D"
09
03
b11 )
b11 2
b110 B
b110 Y
b1 A
b1 X
b1 o
b1 -"
0$
0'
b0 5
b11011 #
b11011 &
b100100 "
b100100 %
#50000
11"
04"
0G"
0F"
0B"
0\
0A"
1_
0="
1m
1s
1%"
1*"
1v
1l
1!"
1&"
1+"
b11100 u
0<"
0R
0W
b1 +
b1 I"
b1 F
0i
1h
b1111 ^
0n
b1 ,
b1 J"
b1 ]
b11101 -
b11101 O"
08"
b1 3"
1>
0P"
1@
1{
0""
1'"
1,"
b11101 .
b11101 M"
b1101 t
19"
1>"
1C"
1H"
b11111 /
b11111 N"
b1111 2"
b1110100111 !
b1110100111 (
1:
b1 *
b1 K"
0O
0T
1f
1k
1x
1}
1$"
1)"
06"
0;"
0@"
0E"
1;
b11 4
1L"
0=
b0 C
b111 Z
b1111 q
b0 /"
17
0w
1|
1#"
1("
05"
1:"
1?"
1D"
19
13
b111 )
b1 2
b10 1
b0 B
b0 Y
b1111 p
b1111 ."
b1 0
b1110 o
b1110 -"
1$
1'
b11 5
b111100010 #
b111100010 &
b111000101 "
b111000101 %
#60000
01"
14"
1G"
1P"
1E
1F"
1H
1B"
1V
1A"
1="
1U
0s
1Q
b1100 G
1<"
06
0%"
0*"
0v
0>
0{
09"
18"
b11111 3"
0?
b1001 *
b1001 K"
0!"
0&"
b0 -
b0 O"
0+"
b0 u
0:
1@
0R
0W
b1001 +
b1001 I"
b1 F
0i
1n
b101 ,
b101 J"
b101 ]
0""
0'"
0,"
b0 .
b0 M"
b0 t
0>"
0C"
0H"
b0 /
b0 N"
b0 2"
b111 !
b111 (
1O
0f
0x
0}
0$"
0)"
16"
1;"
1@"
1E"
1;
b11 4
0L"
08
b10 C
b101 Z
b0 q
b1111 /"
1<
1N
1S
1e
1j
0|
0#"
0("
0:"
0?"
0D"
09
03
b11 )
b0 2
b0 1
b10 B
b10 Y
b0 p
b0 ."
b11 0
b111 A
b111 X
b0 o
b0 -"
0$
0'
b0 5
b1000 #
b1000 &
b11111 "
b11111 %
#70000
0E
0H
0V
1\
0U
0_
0Q
b0 G
0m
b111 ^
b1 -
b1 O"
1>
1P"
1@
0R
1W
b101 +
b101 I"
b101 F
0i
1n
b1101 ,
b1101 J"
b101 ]
1{
b1 .
b1 M"
b1 t
19"
b1 /
b1 N"
b1 2"
b110111 !
b110111 (
1:
b1101 *
b1101 K"
0O
1T
1f
0k
1;
b11 4
1L"
18
b100 C
b11 Z
0<
0N
0S
0e
0j
1w
15"
19
13
b111 )
b1 2
b10 1
b100 B
b100 Y
b1 0
b1 A
b1 X
b1 o
b1 -"
1$
1'
b11 5
b10010 #
b10010 &
b100101 "
b100101 %
#80000
0l
0h
1E
1i
1\
1H
0g
0_
0>
06
1V
b1000 G
0c
0m
b1 ^
b1110 -
b1110 O"
0:
1P"
1@
0?
1M
0W
b1001 +
b1001 I"
b1 F
1d
1n
b1111 ,
b1111 J"
b111 ]
0{
1""
1'"
1,"
b1110 .
b1110 M"
b1110 t
09"
1>"
1C"
1H"
b1110 /
b1110 N"
b1110 2"
b111000111 !
b111000111 (
b1001 *
b1001 K"
1J
0a
1;
b11 4
0L"
08
1=
b101 C
b10 Z
0I
1S
0`
1j
0w
1|
1#"
1("
05"
1:"
1?"
1D"
09
03
b11 )
b10 2
b101 B
b101 Y
b100 A
b100 X
b1110 o
b1110 -"
0$
0'
b0 5
b10110 #
b10110 &
b111010001 "
b111010001 %
#90000
0P"
0\
1_
1m
1l
1h
0R
0E
0i
0P
0H
1g
0L
0V
b0 G
1c
b1111 ^
b0 -
b0 O"
1M
0W
b1 +
b1 I"
b1 F
1d
0n
b1 ,
b1 J"
b1 ]
0""
0'"
0,"
b0 .
b0 M"
b0 t
0>"
0C"
0H"
b0 /
b0 N"
b0 2"
b111 !
b111 (
b1 *
b1 K"
0J
0T
1a
1k
1;
b11 4
1L"
0=
b0 C
b111 Z
07
1<
1I
0S
1`
0j
0|
0#"
0("
0:"
0?"
0D"
19
13
b111 )
b0 2
b11 1
b0 B
b0 Y
b10 0
b1 A
b1 X
b0 o
b0 -"
1$
1'
b1 5
b11 #
b11 &
b110 "
b110 %
#100000
1\
11"
1P"
0_
04"
16
0m
0G"
1?
1E
1s
1H
1v
0@
1V
b1000 G
0l
1+"
b10000 u
0F"
1>
0g
1R
0i
0h
1'"
1C"
0B"
b111 3"
1:
b1101 *
b1101 K"
0c
b1 ^
b11111 -
b11111 O"
1M
0W
b1011 +
b1011 I"
b11 F
1d
1n
b1101 ,
b1101 J"
b101 ]
1{
1""
0,"
b10111 .
b10111 M"
b111 t
19"
1>"
1H"
b11111 /
b11111 N"
b1111 2"
b1111110100 !
b1111110100 (
1J
1O
1T
0a
0f
0k
1$"
1)"
0@"
0E"
0;
b0 4
1L"
18
b111 C
b0 Z
b1100 q
b11 /"
17
0I
1S
0`
1j
1w
1|
1("
15"
1:"
1D"
09
13
b100 )
b1 2
b1 1
b111 B
b111 Y
b1100 p
b1100 ."
b11 0
b100 A
b100 X
b1011 o
b1011 -"
0$
0'
b110 5
b110011101 #
b110011101 &
b101110011 "
b101110011 %
#110000
0P"
1s
01"
1l
1v
14"
0E
1h
b101 ^
1+"
1G"
0U
0H
1*"
0<"
0A"
0F"
0,"
0H"
0Q
0V
b0 G
1&"
b11000 u
08"
0="
b10011 -
b10011 O"
0B"
b10001 3"
1@
1R
1W
b111 +
b111 I"
b111 F
0i
1n
b1101 ,
b1101 J"
b101 ]
1{
1""
0'"
b10011 .
b10011 M"
b11 t
19"
0>"
1C"
b101 /
b101 N"
b101 2"
b1001111111 !
b1001111111 (
b111 *
b111 K"
0O
1f
1x
1}
0)"
06"
0;"
1E"
1;
b11 4
0L"
1=
b101 C
b10 Z
b111 q
b1000 /"
1N
0S
1e
0j
0w
0|
1#"
05"
0:"
1?"
19
03
b11 )
b11 2
b0 1
b101 B
b101 Y
b111 p
b111 ."
b10 A
b10 X
b1100 o
b1100 -"
1$
1'
b111 5
b11110100 #
b11110100 &
b110001011 "
b110001011 %
#120000
0s
0v
0%"
0+"
0!"
1""
1,"
1>"
0~
0*"
1<"
06
0z
b1011 -
b1011 O"
0&"
b0 u
18"
b10011 3"
0P"
0?
1{
0'"
b1011 .
b1011 M"
b1011 t
19"
1C"
b111 /
b111 N"
b111 2"
b101111110 !
b101111110 (
b111 *
b111 K"
0x
0$"
16"
1@"
0;
b10 4
0L"
0=
b10 q
b1101 /"
0<
1w
0#"
15"
0?"
09
03
b10 )
b1 2
b1 1
b10 p
b10 ."
b1 0
b1001 o
b1001 -"
0$
0'
b10 5
b1010101 #
b1010101 &
b100101001 "
b100101001 %
