MACC/Radix_4_Booth_Encode/sqrt_csa_bec.v
module sqrt_csa_bec (
    A,
    B,
    Cin,
    Out
);

input [8:0] A;
input [8:0] B;
input Cin;
output [9:0] Out;

wire [2:0] o_rsa_2bit;

wire [3:0] o_rsa_3bit;
wire [3:0] o_rsa_3bit_add;
wire [3:0] o_rsa_3bit_sub;

wire [4:0] o_rsa_4bit;
wire [4:0] o_rsa_4bit_add;
wire [4:0] o_rsa_4bit_sub;

rsa #(.N(2)) rsa_2bit(  .A(A[1:0]),
                        .B(B[1:0]),
                        .Cin(Cin),
                        .Sum(o_rsa_2bit[1:0]),
                        .Cout(o_rsa_2bit[2]));

rsa #(.N(3)) rsa_3bit(  .A(A[4:2]),
                        .B(B[4:2]),
                        .Cin(1'b0),
                        .Sum(o_rsa_3bit_add[2:0]),
                        .Cout(o_rsa_3bit_add[3]));

rsa #(.N(4)) rsa_4bit(  .A(A[8:5]),
                        .B(B[8:5]),
                        .Cin(1'b0),
                        .Sum(o_rsa_4bit_add[3:0]),
                        .Cout(o_rsa_4bit_add[4]));

// Binary two’s complement block

b2c_4bit bec_rsa_3bit(  .B(o_rsa_3bit_add),
                        .X(o_rsa_3bit_sub));

b2c_5bit bec_rsa_4bit(  .B(o_rsa_4bit_add),
                        .X(o_rsa_4bit_sub));  

mux2to1 #(.N(4)) mux_rsa_3bit(  .In0(o_rsa_3bit_add), 
                                .In1(o_rsa_3bit_sub), 
                                .Sel(o_rsa_2bit[2]), 
                                .Out(o_rsa_3bit));

mux2to1 #(.N(5)) mux_rsa_4bit(  .In0(o_rsa_4bit_add), 
                                .In1(o_rsa_4bit_sub), 
                                .Sel(o_rsa_3bit[3]), 
                                .Out(o_rsa_4bit));

assign Out = {o_rsa_4bit, o_rsa_3bit[2:0], o_rsa_2bit[1:0]};

endmodule                   


///////////////////////////////////////////////////////
module mux2to1 #(parameter N = 9) (
    input  [N-1:0] In0, In1,
    input  Sel,
    output [N-1:0] Out
);
    assign Out = Sel ? In1 : In0;
endmodule

///////////////////////////////////////////////////////
module b2c_4bit (
    input [3:0] B,  
    output [3:0] X   
);
    
    wire [3:0] B_not;

    assign B_not = ~B;

    assign X[0] = ~B_not[0];
    assign X[1] = B_not[1] ^ B_not[0];
    assign X[2] = B_not[2] ^ (B_not[1] & B_not[0]);
    assign X[3] = B_not[3] ^ (B_not[0] & B_not[1] & B_not[2]);

endmodule

///////////////////////////////////////////////////////
module b2c_5bit (
    input [4:0] B,  
    output [4:0] X   
);
    
    wire [1:0] AND_out; // Tín hiệu trung gian từ các cổng AND
    wire [4:0] B_not;

    assign B_not = ~B;

    // Cổng NOT cho bit đầu tiên
    assign X[0] = ~B_not[0];  

    // Nhóm AND-3 và AND-4 theo cấu trúc 2-3-4
    assign AND_out[0] = B_not[0] & B_not[1] & B_not[2];   
    assign AND_out[1] = B_not[0] & B_not[1] & B_not[2] & B_not[3];       // 4-input AND

    // Tính toán các giá trị đầu ra X[i]
    assign X[1] = B_not[1] ^ B_not[0];
    assign X[2] = B_not[2] ^ (B_not[1] & B_not[0]);
    assign X[3] = B_not[3] ^ AND_out[0];
    assign X[4] = B_not[4] ^ AND_out[1];

endmodule

///////////////////////////////////////////////////////
module rsa #( parameter N = 4 ) (
    input  wire [N-1:0] A, B,  // Các toán hạng đầu vào
    input  wire Cin,           // Bit nhớ vào
    output wire [N-1:0] Sum,   // Tổng đầu ra
    output wire Cout           // Bit nhớ ra
);
    wire [N:0] carry;          // Dây để truyền bit nhớ giữa các bộ cộng
    wire [N-1:0] B_xor;        // B XOR với Cin để hỗ trợ phép trừ khi cần

    assign B_xor = B ^ {N{Cin}};  // Nếu Cin = 1, sẽ thực hiện phép trừ A - B
    assign carry[0] = Cin; 
    

    genvar i;
    generate
        for (i = 0; i < N; i = i + 1) begin : adder_stage
            full_adder FA (
                .A(A[i]), 
                .B(B_xor[i]), 
                .Cin(carry[i]), 
                .Sum(Sum[i]), 
                .Cout(carry[i+1])
            );
        end
    endgenerate

    assign carry_sign = carry[N];  
    assign Cout = carry_sign ^ Cin;  // Xữ lý bit có dấu khi trừ

endmodule


// Full Adder 1-bit
module full_adder (
    input  wire A, B, Cin,  
    output wire Sum, Cout   
);
    assign Sum  = A ^ B ^ Cin; 
    assign Cout = (A & B) | (A & Cin) | (B & Cin);  
endmodule

MACC/Radix_4_Booth_Encode/b2c_5bit_tb.v
module tb_b2c_5bit;
    reg [4:0] B;
    wire [4:0] X;
    
    // Kết nối với module b2c_5bit
    b2c_5bit uut (
        .B(B),
        .X(X)
    );
    
    initial begin
        $dumpfile("tb_b2c_5bit.vcd");
        $dumpvars(0, tb_b2c_5bit);
        
        // Kiểm tra tất cả các giá trị có thể của B
        B = 5'b00000; #10;
        B = 5'b00001; #10;
        B = 5'b00010; #10;
        B = 5'b00011; #10;
        B = 5'b00100; #10;
        B = 5'b00101; #10;
        B = 5'b00110; #10;
        B = 5'b00111; #10;
        B = 5'b01000; #10;
        B = 5'b01001; #10;
        B = 5'b01010; #10;
        B = 5'b01011; #10;
        B = 5'b01100; #10;
        B = 5'b01101; #10;
        B = 5'b01110; #10;
        B = 5'b01111; #10;
        B = 5'b10000; #10;
        B = 5'b10001; #10;
        B = 5'b10010; #10;
        B = 5'b10011; #10;
        B = 5'b10100; #10;
        B = 5'b10101; #10;
        B = 5'b10110; #10;
        B = 5'b10111; #10;
        B = 5'b11000; #10;
        B = 5'b11001; #10;
        B = 5'b11010; #10;
        B = 5'b11011; #10;
        B = 5'b11100; #10;
        B = 5'b11101; #10;
        B = 5'b11110; #10;
        B = 5'b11111; #10;
        
        $finish;
    end
    
    initial begin
        $display("Time     |    B   |   X   ");
        $monitor("%0t | B = %b(%d)| X = %b", $time, B,B, X);
    end
endmodule

MACC/Radix_4_Booth_Encode/tb_b2c_5bit.vcd
$date
	Mon Mar 31 10:12:10 2025
$end
$version
	Icarus Verilog
$end
$timescale
	1s
$end
$scope module tb_b2c_5bit $end
$var wire 5 ! X [4:0] $end
$var reg 5 " B [4:0] $end
$scope module uut $end
$var wire 2 # AND_out [1:0] $end
$var wire 5 $ B [4:0] $end
$var wire 5 % B_not [4:0] $end
$var wire 5 & X [4:0] $end
$upscope $end
$upscope $end
$enddefinitions $end
#0
$dumpvars
b0 &
b11111 %
b0 $
b11 #
b0 "
b0 !
$end
#10
b0 #
b11111 !
b11111 &
b11110 %
b1 "
b1 $
#20
b11110 !
b11110 &
b11101 %
b10 "
b10 $
#30
b11101 !
b11101 &
b11100 %
b11 "
b11 $
#40
b11100 !
b11100 &
b11011 %
b100 "
b100 $
#50
b11011 !
b11011 &
b11010 %
b101 "
b101 $
#60
b11010 !
b11010 &
b11001 %
b110 "
b110 $
#70
b11001 !
b11001 &
b11000 %
b111 "
b111 $
#80
b1 #
b11000 !
b11000 &
b10111 %
b1000 "
b1000 $
#90
b0 #
b10111 !
b10111 &
b10110 %
b1001 "
b1001 $
#100
b10110 !
b10110 &
b10101 %
b1010 "
b1010 $
#110
b10101 !
b10101 &
b10100 %
b1011 "
b1011 $
#120
b10100 !
b10100 &
b10011 %
b1100 "
b1100 $
#130
b10011 !
b10011 &
b10010 %
b1101 "
b1101 $
#140
b10010 !
b10010 &
b10001 %
b1110 "
b1110 $
#150
b10001 !
b10001 &
b10000 %
b1111 "
b1111 $
#160
b11 #
b10000 !
b10000 &
b1111 %
b10000 "
b10000 $
#170
b0 #
b1111 !
b1111 &
b1110 %
b10001 "
b10001 $
#180
b1110 !
b1110 &
b1101 %
b10010 "
b10010 $
#190
b1101 !
b1101 &
b1100 %
b10011 "
b10011 $
#200
b1100 !
b1100 &
b1011 %
b10100 "
b10100 $
#210
b1011 !
b1011 &
b1010 %
b10101 "
b10101 $
#220
b1010 !
b1010 &
b1001 %
b10110 "
b10110 $
#230
b1001 !
b1001 &
b1000 %
b10111 "
b10111 $
#240
b1 #
b1000 !
b1000 &
b111 %
b11000 "
b11000 $
#250
b0 #
b111 !
b111 &
b110 %
b11001 "
b11001 $
#260
b110 !
b110 &
b101 %
b11010 "
b11010 $
#270
b101 !
b101 &
b100 %
b11011 "
b11011 $
#280
b100 !
b100 &
b11 %
b11100 "
b11100 $
#290
b11 !
b11 &
b10 %
b11101 "
b11101 $
#300
b10 !
b10 &
b1 %
b11110 "
b11110 $
#310
b1 !
b1 &
b0 %
b11111 "
b11111 $
