MACC/Radix_4_Booth_Encode/b2c_4bit.v
module b2c_4bit (
    input [3:0] B,  
    output [3:0] X   
);
    
    wire [3:0] B_not;

    assign B_not = ~B;

    assign X[0] = ~B_not[0];
    assign X[1] = B_not[1] ^ B_not[0];
    assign X[2] = B_not[2] ^ (B_not[1] & B_not[0]);
    assign X[3] = B_not[3] ^ (B_not[0] & B_not[1] & B_not[2]);

endmodule

MACC/Radix_4_Booth_Encode/b2c_4bit_tb.v
module tb_b2c_4bit;
    reg [3:0] B;
    wire [3:0] X;
    
    // Kết nối với module b2c_4bit
    b2c_4bit uut (
        .B(B),
        .X(X)
    );
    
    initial begin
        $dumpfile("tb_b2c_4bit.vcd");
        $dumpvars(0, tb_b2c_4bit);
        
        // Kiểm tra tất cả các giá trị có thể của B
        B = 4'b0000; #10;
        B = 4'b0001; #10;
        B = 4'b0010; #10;
        B = 4'b0011; #10;
        B = 4'b0100; #10;
        B = 4'b0101; #10;
        B = 4'b0110; #10;
        B = 4'b0111; #10;
        B = 4'b1000; #10;
        B = 4'b1001; #10;
        B = 4'b1010; #10;
        B = 4'b1011; #10;
        B = 4'b1100; #10;
        B = 4'b1101; #10;
        B = 4'b1110; #10;
        B = 4'b1111; #10;
        
        $finish;
    end
    
    initial begin
        $monitor("Time = %0t | B = %b | X = %b", $time, B, X);
    end
endmodule

MACC/Radix_4_Booth_Encode/tb_b2c_4bit.vcd
$date
	Mon Mar 31 10:12:16 2025
$end
$version
	Icarus Verilog
$end
$timescale
	1s
$end
$scope module tb_b2c_4bit $end
$var wire 4 ! X [3:0] $end
$var reg 4 " B [3:0] $end
$scope module uut $end
$var wire 4 # B [3:0] $end
$var wire 4 $ B_not [3:0] $end
$var wire 4 % X [3:0] $end
$upscope $end
$upscope $end
$enddefinitions $end
#0
$dumpvars
b0 %
b1111 $
b0 #
b0 "
b0 !
$end
#10
b1111 !
b1111 %
b1110 $
b1 "
b1 #
#20
b1110 !
b1110 %
b1101 $
b10 "
b10 #
#30
b1101 !
b1101 %
b1100 $
b11 "
b11 #
#40
b1100 !
b1100 %
b1011 $
b100 "
b100 #
#50
b1011 !
b1011 %
b1010 $
b101 "
b101 #
#60
b1010 !
b1010 %
b1001 $
b110 "
b110 #
#70
b1001 !
b1001 %
b1000 $
b111 "
b111 #
#80
b1000 !
b1000 %
b111 $
b1000 "
b1000 #
#90
b111 !
b111 %
b110 $
b1001 "
b1001 #
#100
b110 !
b110 %
b101 $
b1010 "
b1010 #
#110
b101 !
b101 %
b100 $
b1011 "
b1011 #
#120
b100 !
b100 %
b11 $
b1100 "
b1100 #
#130
b11 !
b11 %
b10 $
b1101 "
b1101 #
#140
b10 !
b10 %
b1 $
b1110 "
b1110 #
#150
b1 !
b1 %
b0 $
b1111 "
b1111 #
